spike_starter/__init__.py
spike_starter/__main__.py
spike_starter/spike_starter.py
spike_starter-0.1.7.dist-info/LICENSE
spike_starter-0.1.7.dist-info/METADATA
spike_starter-0.1.7.dist-info/WHEEL
spike_starter-0.1.7.dist-info/entry_points.txt
spike_starter-0.1.7.dist-info/top_level.txt
spike_starter-0.1.7.dist-info/RECORD
