Metadata-Version: 2.1
Name: spike-starter
Version: 0.1.7
Summary: spike-starter creates project from blueprint template
Home-page: UNKNOWN
License: MIT
Platform: UNKNOWN
Classifier: Environment :: Console
Classifier: Intended Audience :: Developers
Classifier: Intended Audience :: System Administrators
Classifier: Programming Language :: Python :: 3
Classifier: License :: OSI Approved :: MIT License
Requires-Dist: click
Requires-Dist: decorator
Requires-Dist: GitPython
Provides-Extra: dev
Requires-Dist: pylint ; extra == 'dev'
Requires-Dist: tox ; extra == 'dev'
Requires-Dist: twine ; extra == 'dev'
